setup.cfg
setup.py
django_firefence.egg-info/PKG-INFO
django_firefence.egg-info/SOURCES.txt
django_firefence.egg-info/dependency_links.txt
django_firefence.egg-info/not-zip-safe
django_firefence.egg-info/requires.txt
django_firefence.egg-info/top_level.txt
firefence/__init__.py
firefence/backends.py
firefence/decorators.py
firefence/middleware.py
firefence/rules.py
firefence/settings.py